{
	"info": {
		"_postman_id": "4b9467c5-35dd-43cf-9d15-58daf91862e0",
		"name": "Redocly Museum API",
		"description": "Imaginary, but delightful Museum API for interacting with museum services and information. Built with love by Redocly.\n\nContact Support:\n Email: team@redocly.com",
		"schema": "https://schema.getpostman.com/json/collection/v2.1.0/collection.json",
		"_exporter_id": "47554131",
		"_collection_link": "https://keyurnagvekar03-8550466.postman.co/workspace/3d2070f6-e5a1-4ee9-8018-cc2813b9f035/collection/47554131-4b9467c5-35dd-43cf-9d15-58daf91862e0?action=share&source=collection_link&creator=47554131"
	},
	"item": [
		{
			"name": "special-events",
			"item": [
				{
					"name": "{eventId}",
					"item": [
						{
							"name": "Get special event",
							"request": {
								"method": "GET",
								"header": [
									{
										"key": "Accept",
										"value": "application/json"
									}
								],
								"url": {
									"raw": "{{baseUrl}}/special-events/:eventId",
									"host": [
										"{{baseUrl}}"
									],
									"path": [
										"special-events",
										":eventId"
									],
									"variable": [
										{
											"key": "eventId",
											"value": "dad4bce8-f5cb-4078-a211-995864315e39",
											"description": "(Required) Identifier for a special event."
										}
									]
								},
								"description": "Get details about a special event."
							},
							"response": [
								{
									"name": "Success.",
									"originalRequest": {
										"method": "GET",
										"header": [
											{
												"key": "Authorization",
												"value": "Basic <credentials>",
												"description": "Added as a part of security scheme: basic"
											},
											{
												"key": "Accept",
												"value": "application/json"
											}
										],
										"url": {
											"raw": "{{baseUrl}}/special-events/:eventId",
											"host": [
												"{{baseUrl}}"
											],
											"path": [
												"special-events",
												":eventId"
											],
											"variable": [
												{
													"key": "eventId",
													"value": "dad4bce8-f5cb-4078-a211-995864315e39",
													"description": "(Required) Identifier for a special event."
												}
											]
										}
									},
									"status": "OK",
									"code": 200,
									"_postman_previewlanguage": "json",
									"header": [
										{
											"key": "Content-Type",
											"value": "application/json"
										}
									],
									"cookie": [],
									"body": "{\n  \"eventId\": \"6744a0da-4121-49cd-8479-f8cc20526495\",\n  \"name\": \"Time Traveler Tea Party\",\n  \"location\": \"Temporal Tearoom\",\n  \"eventDescription\": \"Sip tea with important historical figures.\",\n  \"dates\": [\n    \"2023-11-18\",\n    \"2023-11-25\",\n    \"2023-12-02\"\n  ],\n  \"price\": 60\n}"
								},
								{
									"name": "Bad request.",
									"originalRequest": {
										"method": "GET",
										"header": [
											{
												"key": "Authorization",
												"value": "Basic <credentials>",
												"description": "Added as a part of security scheme: basic"
											},
											{
												"key": "Accept",
												"value": "application/problem+json"
											}
										],
										"url": {
											"raw": "{{baseUrl}}/special-events/:eventId",
											"host": [
												"{{baseUrl}}"
											],
											"path": [
												"special-events",
												":eventId"
											],
											"variable": [
												{
													"key": "eventId",
													"value": "dad4bce8-f5cb-4078-a211-995864315e39",
													"description": "(Required) Identifier for a special event."
												}
											]
										}
									},
									"status": "Bad Request",
									"code": 400,
									"_postman_previewlanguage": "json",
									"header": [
										{
											"key": "Content-Type",
											"value": "application/problem+json"
										}
									],
									"cookie": [],
									"body": "{\n  \"type\": \"object\",\n  \"title\": \"Validation failed\"\n}"
								},
								{
									"name": "Not found.",
									"originalRequest": {
										"method": "GET",
										"header": [
											{
												"key": "Authorization",
												"value": "Basic <credentials>",
												"description": "Added as a part of security scheme: basic"
											},
											{
												"key": "Accept",
												"value": "application/problem+json"
											}
										],
										"url": {
											"raw": "{{baseUrl}}/special-events/:eventId",
											"host": [
												"{{baseUrl}}"
											],
											"path": [
												"special-events",
												":eventId"
											],
											"variable": [
												{
													"key": "eventId",
													"value": "dad4bce8-f5cb-4078-a211-995864315e39",
													"description": "(Required) Identifier for a special event."
												}
											]
										}
									},
									"status": "Not Found",
									"code": 404,
									"_postman_previewlanguage": "json",
									"header": [
										{
											"key": "Content-Type",
											"value": "application/problem+json"
										}
									],
									"cookie": [],
									"body": "{\n  \"type\": \"object\",\n  \"title\": \"Validation failed\"\n}"
								}
							]
						},
						{
							"name": "Update special event",
							"request": {
								"method": "PATCH",
								"header": [
									{
										"key": "Content-Type",
										"value": "application/json"
									},
									{
										"key": "Accept",
										"value": "application/json"
									}
								],
								"body": {
									"mode": "raw",
									"raw": "{\n  \"location\": \"On the beach.\",\n  \"price\": 15\n}",
									"options": {
										"raw": {
											"language": "json"
										}
									}
								},
								"url": {
									"raw": "{{baseUrl}}/special-events/:eventId",
									"host": [
										"{{baseUrl}}"
									],
									"path": [
										"special-events",
										":eventId"
									],
									"variable": [
										{
											"key": "eventId",
											"value": "dad4bce8-f5cb-4078-a211-995864315e39",
											"description": "(Required) Identifier for a special event."
										}
									]
								},
								"description": "Update the details of a special event."
							},
							"response": [
								{
									"name": "Success.",
									"originalRequest": {
										"method": "PATCH",
										"header": [
											{
												"key": "Authorization",
												"value": "Basic <credentials>",
												"description": "Added as a part of security scheme: basic"
											},
											{
												"key": "Accept",
												"value": "application/json"
											}
										],
										"body": {
											"mode": "raw",
											"raw": "{\n  \"location\": \"On the beach.\",\n  \"price\": 15\n}",
											"options": {
												"raw": {
													"language": "json"
												}
											}
										},
										"url": {
											"raw": "{{baseUrl}}/special-events/:eventId",
											"host": [
												"{{baseUrl}}"
											],
											"path": [
												"special-events",
												":eventId"
											],
											"variable": [
												{
													"key": "eventId",
													"value": "dad4bce8-f5cb-4078-a211-995864315e39",
													"description": "(Required) Identifier for a special event."
												}
											]
										}
									},
									"status": "OK",
									"code": 200,
									"_postman_previewlanguage": "json",
									"header": [
										{
											"key": "Content-Type",
											"value": "application/json"
										}
									],
									"cookie": [],
									"body": "{\n  \"eventId\": \"dad4bce8-f5cb-4078-a211-995864315e39\",\n  \"name\": \"Mermaid Treasure Identification and Analysis\",\n  \"location\": \"On the beach.\",\n  \"eventDescription\": \"Join us as we review and classify a rare collection of 20 thingamabobs, gadgets, gizmos, whoosits, and whatsits, kindly donated by Ariel.\",\n  \"dates\": [\n    \"2023-09-05\",\n    \"2023-09-08\"\n  ],\n  \"price\": 15\n}"
								},
								{
									"name": "Bad request.",
									"originalRequest": {
										"method": "PATCH",
										"header": [
											{
												"key": "Authorization",
												"value": "Basic <credentials>",
												"description": "Added as a part of security scheme: basic"
											},
											{
												"key": "Accept",
												"value": "application/problem+json"
											}
										],
										"body": {
											"mode": "raw",
											"raw": "{\n  \"location\": \"On the beach.\",\n  \"price\": 15\n}",
											"options": {
												"raw": {
													"language": "json"
												}
											}
										},
										"url": {
											"raw": "{{baseUrl}}/special-events/:eventId",
											"host": [
												"{{baseUrl}}"
											],
											"path": [
												"special-events",
												":eventId"
											],
											"variable": [
												{
													"key": "eventId",
													"value": "dad4bce8-f5cb-4078-a211-995864315e39",
													"description": "(Required) Identifier for a special event."
												}
											]
										}
									},
									"status": "Bad Request",
									"code": 400,
									"_postman_previewlanguage": "json",
									"header": [
										{
											"key": "Content-Type",
											"value": "application/problem+json"
										}
									],
									"cookie": [],
									"body": "{\n  \"type\": \"object\",\n  \"title\": \"Validation failed\"\n}"
								},
								{
									"name": "Not found.",
									"originalRequest": {
										"method": "PATCH",
										"header": [
											{
												"key": "Authorization",
												"value": "Basic <credentials>",
												"description": "Added as a part of security scheme: basic"
											},
											{
												"key": "Accept",
												"value": "application/problem+json"
											}
										],
										"body": {
											"mode": "raw",
											"raw": "{\n  \"location\": \"On the beach.\",\n  \"price\": 15\n}",
											"options": {
												"raw": {
													"language": "json"
												}
											}
										},
										"url": {
											"raw": "{{baseUrl}}/special-events/:eventId",
											"host": [
												"{{baseUrl}}"
											],
											"path": [
												"special-events",
												":eventId"
											],
											"variable": [
												{
													"key": "eventId",
													"value": "dad4bce8-f5cb-4078-a211-995864315e39",
													"description": "(Required) Identifier for a special event."
												}
											]
										}
									},
									"status": "Not Found",
									"code": 404,
									"_postman_previewlanguage": "json",
									"header": [
										{
											"key": "Content-Type",
											"value": "application/problem+json"
										}
									],
									"cookie": [],
									"body": "{\n  \"type\": \"object\",\n  \"title\": \"Validation failed\"\n}"
								}
							]
						},
						{
							"name": "Delete special event",
							"request": {
								"method": "DELETE",
								"header": [
									{
										"key": "Accept",
										"value": "application/problem+json"
									}
								],
								"url": {
									"raw": "{{baseUrl}}/special-events/:eventId",
									"host": [
										"{{baseUrl}}"
									],
									"path": [
										"special-events",
										":eventId"
									],
									"variable": [
										{
											"key": "eventId",
											"value": "dad4bce8-f5cb-4078-a211-995864315e39",
											"description": "(Required) Identifier for a special event."
										}
									]
								},
								"description": "Delete a special event from the collection. Allows museum to cancel planned events."
							},
							"response": [
								{
									"name": "Success - no content.",
									"originalRequest": {
										"method": "DELETE",
										"header": [
											{
												"key": "Authorization",
												"value": "Basic <credentials>",
												"description": "Added as a part of security scheme: basic"
											}
										],
										"url": {
											"raw": "{{baseUrl}}/special-events/:eventId",
											"host": [
												"{{baseUrl}}"
											],
											"path": [
												"special-events",
												":eventId"
											],
											"variable": [
												{
													"key": "eventId",
													"value": "dad4bce8-f5cb-4078-a211-995864315e39",
													"description": "(Required) Identifier for a special event."
												}
											]
										}
									},
									"status": "No Content",
									"code": 204,
									"_postman_previewlanguage": "text",
									"header": [
										{
											"key": "Content-Type",
											"value": "text/plain"
										}
									],
									"cookie": [],
									"body": ""
								},
								{
									"name": "Bad request.",
									"originalRequest": {
										"method": "DELETE",
										"header": [
											{
												"key": "Authorization",
												"value": "Basic <credentials>",
												"description": "Added as a part of security scheme: basic"
											},
											{
												"key": "Accept",
												"value": "application/problem+json"
											}
										],
										"url": {
											"raw": "{{baseUrl}}/special-events/:eventId",
											"host": [
												"{{baseUrl}}"
											],
											"path": [
												"special-events",
												":eventId"
											],
											"variable": [
												{
													"key": "eventId",
													"value": "dad4bce8-f5cb-4078-a211-995864315e39",
													"description": "(Required) Identifier for a special event."
												}
											]
										}
									},
									"status": "Bad Request",
									"code": 400,
									"_postman_previewlanguage": "json",
									"header": [
										{
											"key": "Content-Type",
											"value": "application/problem+json"
										}
									],
									"cookie": [],
									"body": "{\n  \"type\": \"object\",\n  \"title\": \"Validation failed\"\n}"
								},
								{
									"name": "Unauthorized.",
									"originalRequest": {
										"method": "DELETE",
										"header": [
											{
												"key": "Authorization",
												"value": "Basic <credentials>",
												"description": "Added as a part of security scheme: basic"
											},
											{
												"key": "Accept",
												"value": "application/problem+json"
											}
										],
										"url": {
											"raw": "{{baseUrl}}/special-events/:eventId",
											"host": [
												"{{baseUrl}}"
											],
											"path": [
												"special-events",
												":eventId"
											],
											"variable": [
												{
													"key": "eventId",
													"value": "dad4bce8-f5cb-4078-a211-995864315e39",
													"description": "(Required) Identifier for a special event."
												}
											]
										}
									},
									"status": "Unauthorized",
									"code": 401,
									"_postman_previewlanguage": "json",
									"header": [
										{
											"key": "Content-Type",
											"value": "application/problem+json"
										}
									],
									"cookie": [],
									"body": "{\n  \"type\": \"object\",\n  \"title\": \"Validation failed\"\n}"
								},
								{
									"name": "Not found.",
									"originalRequest": {
										"method": "DELETE",
										"header": [
											{
												"key": "Authorization",
												"value": "Basic <credentials>",
												"description": "Added as a part of security scheme: basic"
											},
											{
												"key": "Accept",
												"value": "application/problem+json"
											}
										],
										"url": {
											"raw": "{{baseUrl}}/special-events/:eventId",
											"host": [
												"{{baseUrl}}"
											],
											"path": [
												"special-events",
												":eventId"
											],
											"variable": [
												{
													"key": "eventId",
													"value": "dad4bce8-f5cb-4078-a211-995864315e39",
													"description": "(Required) Identifier for a special event."
												}
											]
										}
									},
									"status": "Not Found",
									"code": 404,
									"_postman_previewlanguage": "json",
									"header": [
										{
											"key": "Content-Type",
											"value": "application/problem+json"
										}
									],
									"cookie": [],
									"body": "{\n  \"type\": \"object\",\n  \"title\": \"Validation failed\"\n}"
								}
							]
						}
					]
				},
				{
					"name": "Create special events",
					"request": {
						"method": "POST",
						"header": [
							{
								"key": "Content-Type",
								"value": "application/json"
							},
							{
								"key": "Accept",
								"value": "application/json"
							}
						],
						"body": {
							"mode": "raw",
							"raw": "{\n  \"name\": \"Mermaid Treasure Identification and Analysis\",\n  \"location\": \"Under the seaaa 🦀 🎶 🌊.\",\n  \"eventDescription\": \"Join us as we review and classify a rare collection of 20 thingamabobs, gadgets, gizmos, whoosits, and whatsits, kindly donated by Ariel.\",\n  \"dates\": [\n    \"2023-09-05\",\n    \"2023-09-08\"\n  ],\n  \"price\": 0\n}",
							"options": {
								"raw": {
									"language": "json"
								}
							}
						},
						"url": {
							"raw": "{{baseUrl}}/special-events",
							"host": [
								"{{baseUrl}}"
							],
							"path": [
								"special-events"
							]
						},
						"description": "Creates a new special event for the museum."
					},
					"response": [
						{
							"name": "Created.",
							"originalRequest": {
								"method": "POST",
								"header": [
									{
										"key": "Authorization",
										"value": "Basic <credentials>",
										"description": "Added as a part of security scheme: basic"
									},
									{
										"key": "Accept",
										"value": "application/json"
									}
								],
								"body": {
									"mode": "raw",
									"raw": "{\n  \"name\": \"Mermaid Treasure Identification and Analysis\",\n  \"location\": \"Under the seaaa 🦀 🎶 🌊.\",\n  \"eventDescription\": \"Join us as we review and classify a rare collection of 20 thingamabobs, gadgets, gizmos, whoosits, and whatsits, kindly donated by Ariel.\",\n  \"dates\": [\n    \"2023-09-05\",\n    \"2023-09-08\"\n  ],\n  \"price\": 0\n}",
									"options": {
										"raw": {
											"language": "json"
										}
									}
								},
								"url": {
									"raw": "{{baseUrl}}/special-events",
									"host": [
										"{{baseUrl}}"
									],
									"path": [
										"special-events"
									]
								}
							},
							"status": "Created",
							"code": 201,
							"_postman_previewlanguage": "json",
							"header": [
								{
									"key": "Content-Type",
									"value": "application/json"
								}
							],
							"cookie": [],
							"body": "{\n  \"eventId\": \"dad4bce8-f5cb-4078-a211-995864315e39\",\n  \"name\": \"Mermaid Treasure Identification and Analysis\",\n  \"location\": \"Under the seaaa 🦀 🎶 🌊.\",\n  \"eventDescription\": \"Join us as we review and classify a rare collection of 20 thingamabobs, gadgets, gizmos, whoosits, and whatsits, kindly donated by Ariel.\",\n  \"dates\": [\n    \"2023-09-05\",\n    \"2023-09-08\"\n  ],\n  \"price\": 30\n}"
						},
						{
							"name": "Bad request.",
							"originalRequest": {
								"method": "POST",
								"header": [
									{
										"key": "Authorization",
										"value": "Basic <credentials>",
										"description": "Added as a part of security scheme: basic"
									},
									{
										"key": "Accept",
										"value": "application/problem+json"
									}
								],
								"body": {
									"mode": "raw",
									"raw": "{\n  \"name\": \"Mermaid Treasure Identification and Analysis\",\n  \"location\": \"Under the seaaa 🦀 🎶 🌊.\",\n  \"eventDescription\": \"Join us as we review and classify a rare collection of 20 thingamabobs, gadgets, gizmos, whoosits, and whatsits, kindly donated by Ariel.\",\n  \"dates\": [\n    \"2023-09-05\",\n    \"2023-09-08\"\n  ],\n  \"price\": 0\n}",
									"options": {
										"raw": {
											"language": "json"
										}
									}
								},
								"url": {
									"raw": "{{baseUrl}}/special-events",
									"host": [
										"{{baseUrl}}"
									],
									"path": [
										"special-events"
									]
								}
							},
							"status": "Bad Request",
							"code": 400,
							"_postman_previewlanguage": "json",
							"header": [
								{
									"key": "Content-Type",
									"value": "application/problem+json"
								}
							],
							"cookie": [],
							"body": "{\n  \"type\": \"object\",\n  \"title\": \"Validation failed\"\n}"
						},
						{
							"name": "Not found.",
							"originalRequest": {
								"method": "POST",
								"header": [
									{
										"key": "Authorization",
										"value": "Basic <credentials>",
										"description": "Added as a part of security scheme: basic"
									},
									{
										"key": "Accept",
										"value": "application/problem+json"
									}
								],
								"body": {
									"mode": "raw",
									"raw": "{\n  \"name\": \"Mermaid Treasure Identification and Analysis\",\n  \"location\": \"Under the seaaa 🦀 🎶 🌊.\",\n  \"eventDescription\": \"Join us as we review and classify a rare collection of 20 thingamabobs, gadgets, gizmos, whoosits, and whatsits, kindly donated by Ariel.\",\n  \"dates\": [\n    \"2023-09-05\",\n    \"2023-09-08\"\n  ],\n  \"price\": 0\n}",
									"options": {
										"raw": {
											"language": "json"
										}
									}
								},
								"url": {
									"raw": "{{baseUrl}}/special-events",
									"host": [
										"{{baseUrl}}"
									],
									"path": [
										"special-events"
									]
								}
							},
							"status": "Not Found",
							"code": 404,
							"_postman_previewlanguage": "json",
							"header": [
								{
									"key": "Content-Type",
									"value": "application/problem+json"
								}
							],
							"cookie": [],
							"body": "{\n  \"type\": \"object\",\n  \"title\": \"Validation failed\"\n}"
						}
					]
				},
				{
					"name": "List special events",
					"request": {
						"method": "GET",
						"header": [
							{
								"key": "Accept",
								"value": "application/json"
							}
						],
						"url": {
							"raw": "{{baseUrl}}/special-events?startDate=2023-02-23&endDate=2023-04-18&page=2&limit=15",
							"host": [
								"{{baseUrl}}"
							],
							"path": [
								"special-events"
							],
							"query": [
								{
									"key": "startDate",
									"value": "2023-02-23",
									"description": "Starting date to retrieve future operating hours from. Defaults to today's date."
								},
								{
									"key": "endDate",
									"value": "2023-04-18",
									"description": "End of a date range to retrieve special events for. Defaults to 7 days after `startDate`."
								},
								{
									"key": "page",
									"value": "2",
									"description": "Page number to retrieve."
								},
								{
									"key": "limit",
									"value": "15",
									"description": "Number of days per page."
								}
							]
						},
						"description": "Return a list of upcoming special events at the museum."
					},
					"response": [
						{
							"name": "Success.",
							"originalRequest": {
								"method": "GET",
								"header": [
									{
										"key": "Authorization",
										"value": "Basic <credentials>",
										"description": "Added as a part of security scheme: basic"
									},
									{
										"key": "Accept",
										"value": "application/json"
									}
								],
								"url": {
									"raw": "{{baseUrl}}/special-events?startDate=2023-02-23&endDate=2023-04-18&page=2&limit=15",
									"host": [
										"{{baseUrl}}"
									],
									"path": [
										"special-events"
									],
									"query": [
										{
											"key": "startDate",
											"value": "2023-02-23"
										},
										{
											"key": "endDate",
											"value": "2023-04-18"
										},
										{
											"key": "page",
											"value": "2"
										},
										{
											"key": "limit",
											"value": "15"
										}
									]
								}
							},
							"status": "OK",
							"code": 200,
							"_postman_previewlanguage": "json",
							"header": [
								{
									"key": "Content-Type",
									"value": "application/json"
								}
							],
							"cookie": [],
							"body": "[\n  {\n    \"eventId\": \"f3e0e76e-e4a8-466e-ab9c-ae36c15b8e97\",\n    \"name\": \"Sasquatch Ballet\",\n    \"location\": \"Seattle... probably\",\n    \"eventDescription\": \"They're big, they're hairy, but they're also graceful. Come learn how the biggest feet can have the lightest touch.\",\n    \"dates\": [\n      \"2023-12-15\",\n      \"2023-12-22\"\n    ],\n    \"price\": 40\n  },\n  {\n    \"eventId\": \"2f14374a-9c65-4ee5-94b7-fba66d893483\",\n    \"name\": \"Solar Telescope Demonstration\",\n    \"location\": \"Far from the sun.\",\n    \"eventDescription\": \"Look at the sun without going blind!\",\n    \"dates\": [\n      \"2023-09-07\",\n      \"2023-09-14\"\n    ],\n    \"price\": 50\n  },\n  {\n    \"eventId\": \"6aaa61ba-b2aa-4868-b803-603dbbf7bfdb\",\n    \"name\": \"Cook like a Caveman\",\n    \"location\": \"Fire Pit on East side\",\n    \"eventDescription\": \"Learn to cook on an open flame.\",\n    \"dates\": [\n      \"2023-11-10\",\n      \"2023-11-17\",\n      \"2023-11-24\"\n    ],\n    \"price\": 5\n  },\n  {\n    \"eventId\": \"602b75e1-5696-4ab8-8c7a-f9e13580f910\",\n    \"name\": \"Underwater Basket Weaving\",\n    \"location\": \"Rec Center Pool next door.\",\n    \"eventDescription\": \"Learn to weave baskets underwater.\",\n    \"dates\": [\n      \"2023-09-12\",\n      \"2023-09-15\"\n    ],\n    \"price\": 15\n  },\n  {\n    \"eventId\": \"dad4bce8-f5cb-4078-a211-995864315e39\",\n    \"name\": \"Mermaid Treasure Identification and Analysis\",\n    \"location\": \"Room Sea-12\",\n    \"eventDescription\": \"Join us as we review and classify a rare collection of 20 thingamabobs, gadgets, gizmos, whoosits, and whatsits — kindly donated by Ariel.\",\n    \"dates\": [\n      \"2023-09-05\",\n      \"2023-09-08\"\n    ],\n    \"price\": 30\n  },\n  {\n    \"eventId\": \"6744a0da-4121-49cd-8479-f8cc20526495\",\n    \"name\": \"Time Traveler Tea Party\",\n    \"location\": \"Temporal Tearoom\",\n    \"eventDescription\": \"Sip tea with important historical figures.\",\n    \"dates\": [\n      \"2023-11-18\",\n      \"2023-11-25\",\n      \"2023-12-02\"\n    ],\n    \"price\": 60\n  },\n  {\n    \"eventId\": \"3be6453c-03eb-4357-ae5a-984a0e574a54\",\n    \"name\": \"Pirate Coding Workshop\",\n    \"location\": \"Computer Room\",\n    \"eventDescription\": \"Captain Blackbeard shares his love of the C...language. And possibly Arrrrr (R lang).\",\n    \"dates\": [\n      \"2023-10-29\",\n      \"2023-10-30\",\n      \"2023-10-31\"\n    ],\n    \"price\": 45\n  },\n  {\n    \"eventId\": \"9d90d29a-2af5-4206-97d9-9ea9ceadcb78\",\n    \"name\": \"Llama Street Art Through the Ages\",\n    \"location\": \"Auditorium\",\n    \"eventDescription\": \"Llama street art?! Alpaca my bags -- let's go!\",\n    \"dates\": [\n      \"2023-10-29\",\n      \"2023-10-30\",\n      \"2023-10-31\"\n    ],\n    \"price\": 45\n  },\n  {\n    \"eventId\": \"a3c7b2c4-b5fb-4ef7-9322-00a919864957\",\n    \"name\": \"The Great Parrot Debate\",\n    \"location\": \"Outdoor Amphitheatre\",\n    \"eventDescription\": \"See leading parrot minds discuss important geopolitical issues.\",\n    \"dates\": [\n      \"2023-11-03\",\n      \"2023-11-10\"\n    ],\n    \"price\": 35\n  },\n  {\n    \"eventId\": \"b92d46b7-4c5d-422b-87a5-287767e26f29\",\n    \"name\": \"Eat a Bunch of Corn\",\n    \"location\": \"Cafeteria\",\n    \"eventDescription\": \"We accidentally bought too much corn. Please come eat it.\",\n    \"dates\": [\n      \"2023-11-10\",\n      \"2023-11-17\",\n      \"2023-11-24\"\n    ],\n    \"price\": 5\n  }\n]"
						},
						{
							"name": "Bad request.",
							"originalRequest": {
								"method": "GET",
								"header": [
									{
										"key": "Authorization",
										"value": "Basic <credentials>",
										"description": "Added as a part of security scheme: basic"
									},
									{
										"key": "Accept",
										"value": "application/problem+json"
									}
								],
								"url": {
									"raw": "{{baseUrl}}/special-events?startDate=2023-02-23&endDate=2023-04-18&page=2&limit=15",
									"host": [
										"{{baseUrl}}"
									],
									"path": [
										"special-events"
									],
									"query": [
										{
											"key": "startDate",
											"value": "2023-02-23"
										},
										{
											"key": "endDate",
											"value": "2023-04-18"
										},
										{
											"key": "page",
											"value": "2"
										},
										{
											"key": "limit",
											"value": "15"
										}
									]
								}
							},
							"status": "Bad Request",
							"code": 400,
							"_postman_previewlanguage": "json",
							"header": [
								{
									"key": "Content-Type",
									"value": "application/problem+json"
								}
							],
							"cookie": [],
							"body": "{\n  \"type\": \"object\",\n  \"title\": \"Validation failed\"\n}"
						},
						{
							"name": "Not found.",
							"originalRequest": {
								"method": "GET",
								"header": [
									{
										"key": "Authorization",
										"value": "Basic <credentials>",
										"description": "Added as a part of security scheme: basic"
									},
									{
										"key": "Accept",
										"value": "application/problem+json"
									}
								],
								"url": {
									"raw": "{{baseUrl}}/special-events?startDate=2023-02-23&endDate=2023-04-18&page=2&limit=15",
									"host": [
										"{{baseUrl}}"
									],
									"path": [
										"special-events"
									],
									"query": [
										{
											"key": "startDate",
											"value": "2023-02-23"
										},
										{
											"key": "endDate",
											"value": "2023-04-18"
										},
										{
											"key": "page",
											"value": "2"
										},
										{
											"key": "limit",
											"value": "15"
										}
									]
								}
							},
							"status": "Not Found",
							"code": 404,
							"_postman_previewlanguage": "json",
							"header": [
								{
									"key": "Content-Type",
									"value": "application/problem+json"
								}
							],
							"cookie": [],
							"body": "{\n  \"type\": \"object\",\n  \"title\": \"Validation failed\"\n}"
						}
					]
				}
			]
		},
		{
			"name": "tickets",
			"item": [
				{
					"name": "Buy museum tickets",
					"request": {
						"method": "POST",
						"header": [
							{
								"key": "Content-Type",
								"value": "application/json"
							},
							{
								"key": "Accept",
								"value": "application/json"
							}
						],
						"body": {
							"mode": "raw",
							"raw": "{\n  \"ticketType\": \"general\",\n  \"ticketDate\": \"2023-09-07\",\n  \"email\": \"todd@example.com\"\n}",
							"options": {
								"raw": {
									"language": "json"
								}
							}
						},
						"url": {
							"raw": "{{baseUrl}}/tickets",
							"host": [
								"{{baseUrl}}"
							],
							"path": [
								"tickets"
							]
						},
						"description": "Purchase museum tickets for general entry or special events."
					},
					"response": [
						{
							"name": "Created.",
							"originalRequest": {
								"method": "POST",
								"header": [
									{
										"key": "Authorization",
										"value": "Basic <credentials>",
										"description": "Added as a part of security scheme: basic"
									},
									{
										"key": "Accept",
										"value": "application/json"
									}
								],
								"body": {
									"mode": "raw",
									"raw": "{\n  \"ticketType\": \"general\",\n  \"ticketDate\": \"2023-09-07\",\n  \"email\": \"todd@example.com\"\n}",
									"options": {
										"raw": {
											"language": "json"
										}
									}
								},
								"url": {
									"raw": "{{baseUrl}}/tickets",
									"host": [
										"{{baseUrl}}"
									],
									"path": [
										"tickets"
									]
								}
							},
							"status": "Created",
							"code": 201,
							"_postman_previewlanguage": "json",
							"header": [
								{
									"key": "Content-Type",
									"value": "application/json"
								}
							],
							"cookie": [],
							"body": "{\n  \"message\": \"Museum general entry ticket purchased\",\n  \"ticketId\": \"382c0820-0530-4f4b-99af-13811ad0f17a\",\n  \"ticketType\": \"general\",\n  \"ticketDate\": \"2023-09-07\",\n  \"confirmationCode\": \"ticket-general-e5e5c6-dce78\"\n}"
						},
						{
							"name": "Bad request.",
							"originalRequest": {
								"method": "POST",
								"header": [
									{
										"key": "Authorization",
										"value": "Basic <credentials>",
										"description": "Added as a part of security scheme: basic"
									},
									{
										"key": "Accept",
										"value": "application/problem+json"
									}
								],
								"body": {
									"mode": "raw",
									"raw": "{\n  \"ticketType\": \"general\",\n  \"ticketDate\": \"2023-09-07\",\n  \"email\": \"todd@example.com\"\n}",
									"options": {
										"raw": {
											"language": "json"
										}
									}
								},
								"url": {
									"raw": "{{baseUrl}}/tickets",
									"host": [
										"{{baseUrl}}"
									],
									"path": [
										"tickets"
									]
								}
							},
							"status": "Bad Request",
							"code": 400,
							"_postman_previewlanguage": "json",
							"header": [
								{
									"key": "Content-Type",
									"value": "application/problem+json"
								}
							],
							"cookie": [],
							"body": "{\n  \"type\": \"object\",\n  \"title\": \"Validation failed\"\n}"
						},
						{
							"name": "Not found.",
							"originalRequest": {
								"method": "POST",
								"header": [
									{
										"key": "Authorization",
										"value": "Basic <credentials>",
										"description": "Added as a part of security scheme: basic"
									},
									{
										"key": "Accept",
										"value": "application/problem+json"
									}
								],
								"body": {
									"mode": "raw",
									"raw": "{\n  \"ticketType\": \"general\",\n  \"ticketDate\": \"2023-09-07\",\n  \"email\": \"todd@example.com\"\n}",
									"options": {
										"raw": {
											"language": "json"
										}
									}
								},
								"url": {
									"raw": "{{baseUrl}}/tickets",
									"host": [
										"{{baseUrl}}"
									],
									"path": [
										"tickets"
									]
								}
							},
							"status": "Not Found",
							"code": 404,
							"_postman_previewlanguage": "json",
							"header": [
								{
									"key": "Content-Type",
									"value": "application/problem+json"
								}
							],
							"cookie": [],
							"body": "{\n  \"type\": \"object\",\n  \"title\": \"Validation failed\"\n}"
						}
					]
				},
				{
					"name": "Get ticket QR code",
					"request": {
						"method": "GET",
						"header": [
							{
								"key": "Accept",
								"value": "image/png"
							}
						],
						"url": {
							"raw": "{{baseUrl}}/tickets/:ticketId/qr",
							"host": [
								"{{baseUrl}}"
							],
							"path": [
								"tickets",
								":ticketId",
								"qr"
							],
							"variable": [
								{
									"key": "ticketId",
									"value": "a54a57ca-36f8-421b-a6b4-2e8f26858a4c",
									"description": "(Required) Identifier for a ticket to a museum event. Used to generate ticket image."
								}
							]
						},
						"description": "Return an image of your ticket with scannable QR code. Used for event entry."
					},
					"response": [
						{
							"name": "Scannable event ticket in image format.",
							"originalRequest": {
								"method": "GET",
								"header": [
									{
										"key": "Authorization",
										"value": "Basic <credentials>",
										"description": "Added as a part of security scheme: basic"
									},
									{
										"key": "Accept",
										"value": "image/png"
									}
								],
								"url": {
									"raw": "{{baseUrl}}/tickets/:ticketId/qr",
									"host": [
										"{{baseUrl}}"
									],
									"path": [
										"tickets",
										":ticketId",
										"qr"
									],
									"variable": [
										{
											"key": "ticketId",
											"value": "a54a57ca-36f8-421b-a6b4-2e8f26858a4c",
											"description": "(Required) Identifier for a ticket to a museum event. Used to generate ticket image."
										}
									]
								}
							},
							"status": "OK",
							"code": 200,
							"_postman_previewlanguage": "text",
							"header": [
								{
									"key": "Content-Type",
									"value": "image/png"
								}
							],
							"cookie": [],
							"body": "string"
						},
						{
							"name": "Bad request.",
							"originalRequest": {
								"method": "GET",
								"header": [
									{
										"key": "Authorization",
										"value": "Basic <credentials>",
										"description": "Added as a part of security scheme: basic"
									},
									{
										"key": "Accept",
										"value": "application/problem+json"
									}
								],
								"url": {
									"raw": "{{baseUrl}}/tickets/:ticketId/qr",
									"host": [
										"{{baseUrl}}"
									],
									"path": [
										"tickets",
										":ticketId",
										"qr"
									],
									"variable": [
										{
											"key": "ticketId",
											"value": "a54a57ca-36f8-421b-a6b4-2e8f26858a4c",
											"description": "(Required) Identifier for a ticket to a museum event. Used to generate ticket image."
										}
									]
								}
							},
							"status": "Bad Request",
							"code": 400,
							"_postman_previewlanguage": "json",
							"header": [
								{
									"key": "Content-Type",
									"value": "application/problem+json"
								}
							],
							"cookie": [],
							"body": "{\n  \"type\": \"object\",\n  \"title\": \"Validation failed\"\n}"
						},
						{
							"name": "Not found.",
							"originalRequest": {
								"method": "GET",
								"header": [
									{
										"key": "Authorization",
										"value": "Basic <credentials>",
										"description": "Added as a part of security scheme: basic"
									},
									{
										"key": "Accept",
										"value": "application/problem+json"
									}
								],
								"url": {
									"raw": "{{baseUrl}}/tickets/:ticketId/qr",
									"host": [
										"{{baseUrl}}"
									],
									"path": [
										"tickets",
										":ticketId",
										"qr"
									],
									"variable": [
										{
											"key": "ticketId",
											"value": "a54a57ca-36f8-421b-a6b4-2e8f26858a4c",
											"description": "(Required) Identifier for a ticket to a museum event. Used to generate ticket image."
										}
									]
								}
							},
							"status": "Not Found",
							"code": 404,
							"_postman_previewlanguage": "json",
							"header": [
								{
									"key": "Content-Type",
									"value": "application/problem+json"
								}
							],
							"cookie": [],
							"body": "{\n  \"type\": \"object\",\n  \"title\": \"Validation failed\"\n}"
						}
					]
				}
			]
		},
		{
			"name": "Get museum hours",
			"event": [
				{
					"listen": "prerequest",
					"script": {
						"exec": [
							"// Generate a dummy token before request\r",
							"const token = \"Bearer \" + Buffer.from(Math.random().toString()).toString(\"base64\");\r",
							"pm.environment.set(\"authToken\", token);\r",
							""
						],
						"type": "text/javascript",
						"packages": {}
					}
				}
			],
			"request": {
				"method": "GET",
				"header": [
					{
						"key": "Accept",
						"value": "application/json"
					}
				],
				"url": {
					"raw": "{{baseUrl}}/museum-hours?startDate=2023-02-23&page=2&limit=15",
					"host": [
						"{{baseUrl}}"
					],
					"path": [
						"museum-hours"
					],
					"query": [
						{
							"key": "startDate",
							"value": "2023-02-23",
							"description": "Starting date to retrieve future operating hours from. Defaults to today's date."
						},
						{
							"key": "page",
							"value": "2",
							"description": "Page number to retrieve."
						},
						{
							"key": "limit",
							"value": "15",
							"description": "Number of days per page."
						}
					]
				},
				"description": "Get upcoming museum operating hours."
			},
			"response": [
				{
					"name": "Success.",
					"originalRequest": {
						"method": "GET",
						"header": [
							{
								"key": "Authorization",
								"value": "Basic <credentials>",
								"description": "Added as a part of security scheme: basic"
							},
							{
								"key": "Accept",
								"value": "application/json"
							}
						],
						"url": {
							"raw": "{{baseUrl}}/museum-hours?startDate=2023-02-23&page=2&limit=15",
							"host": [
								"{{baseUrl}}"
							],
							"path": [
								"museum-hours"
							],
							"query": [
								{
									"key": "startDate",
									"value": "2023-02-23"
								},
								{
									"key": "page",
									"value": "2"
								},
								{
									"key": "limit",
									"value": "15"
								}
							]
						}
					},
					"status": "OK",
					"code": 200,
					"_postman_previewlanguage": "json",
					"header": [
						{
							"key": "Content-Type",
							"value": "application/json"
						}
					],
					"cookie": [],
					"body": "[\n  {\n    \"date\": \"2023-09-11\",\n    \"timeOpen\": \"09:00\",\n    \"timeClose\": \"18:00\"\n  },\n  {\n    \"date\": \"2023-09-12\",\n    \"timeOpen\": \"09:00\",\n    \"timeClose\": \"18:00\"\n  },\n  {\n    \"date\": \"2023-09-13\",\n    \"timeOpen\": \"09:00\",\n    \"timeClose\": \"18:00\"\n  },\n  {\n    \"date\": \"2023-09-14\",\n    \"timeOpen\": \"09:00\",\n    \"timeClose\": \"18:00\"\n  },\n  {\n    \"date\": \"2023-09-15\",\n    \"timeOpen\": \"10:00\",\n    \"timeClose\": \"16:00\"\n  },\n  {\n    \"date\": \"2023-09-18\",\n    \"timeOpen\": \"09:00\",\n    \"timeClose\": \"18:00\"\n  },\n  {\n    \"date\": \"2023-09-19\",\n    \"timeOpen\": \"09:00\",\n    \"timeClose\": \"18:00\"\n  },\n  {\n    \"date\": \"2023-09-20\",\n    \"timeOpen\": \"09:00\",\n    \"timeClose\": \"18:00\"\n  },\n  {\n    \"date\": \"2023-09-21\",\n    \"timeOpen\": \"09:00\",\n    \"timeClose\": \"18:00\"\n  },\n  {\n    \"date\": \"2023-09-22\",\n    \"timeOpen\": \"10:00\",\n    \"timeClose\": \"16:00\"\n  }\n]"
				},
				{
					"name": "Bad request.",
					"originalRequest": {
						"method": "GET",
						"header": [
							{
								"key": "Authorization",
								"value": "Basic <credentials>",
								"description": "Added as a part of security scheme: basic"
							},
							{
								"key": "Accept",
								"value": "application/problem+json"
							}
						],
						"url": {
							"raw": "{{baseUrl}}/museum-hours?startDate=2023-02-23&page=2&limit=15",
							"host": [
								"{{baseUrl}}"
							],
							"path": [
								"museum-hours"
							],
							"query": [
								{
									"key": "startDate",
									"value": "2023-02-23"
								},
								{
									"key": "page",
									"value": "2"
								},
								{
									"key": "limit",
									"value": "15"
								}
							]
						}
					},
					"status": "Bad Request",
					"code": 400,
					"_postman_previewlanguage": "json",
					"header": [
						{
							"key": "Content-Type",
							"value": "application/problem+json"
						}
					],
					"cookie": [],
					"body": "{\n  \"type\": \"object\",\n  \"title\": \"Validation failed\"\n}"
				},
				{
					"name": "Not found.",
					"originalRequest": {
						"method": "GET",
						"header": [
							{
								"key": "Authorization",
								"value": "Basic <credentials>",
								"description": "Added as a part of security scheme: basic"
							},
							{
								"key": "Accept",
								"value": "application/problem+json"
							}
						],
						"url": {
							"raw": "{{baseUrl}}/museum-hours?startDate=2023-02-23&page=2&limit=15",
							"host": [
								"{{baseUrl}}"
							],
							"path": [
								"museum-hours"
							],
							"query": [
								{
									"key": "startDate",
									"value": "2023-02-23"
								},
								{
									"key": "page",
									"value": "2"
								},
								{
									"key": "limit",
									"value": "15"
								}
							]
						}
					},
					"status": "Not Found",
					"code": 404,
					"_postman_previewlanguage": "json",
					"header": [
						{
							"key": "Content-Type",
							"value": "application/problem+json"
						}
					],
					"cookie": [],
					"body": "{\n  \"type\": \"object\",\n  \"title\": \"Validation failed\"\n}"
				}
			]
		}
	],
	"auth": {
		"type": "basic",
		"basic": [
			{
				"key": "username",
				"value": "{{basicAuthUsername}}",
				"type": "string"
			},
			{
				"key": "password",
				"value": "{{basicAuthPassword}}",
				"type": "string"
			}
		]
	},
	"variable": [
		{
			"key": "baseUrl",
			"value": "https://redocly.com/_mock/docs/openapi/museum-api",
			"type": "string"
		}
	]
}